__init__.py
asset_predictor/__init__.py
asset_predictor/data.py
asset_predictor/model.py
asset_predictor/predict.py
asset_predictor-0.1.0.dist-info/METADATA
asset_predictor-0.1.0.dist-info/WHEEL
asset_predictor-0.1.0.dist-info/entry_points.txt
asset_predictor-0.1.0.dist-info/top_level.txt
asset_predictor-0.1.0.dist-info/RECORD
