Metadata-Version: 2.4
Name: asset-predictor
Version: 0.1.0
Summary: Previsão de séries temporais de ativos financeiros usando RNN
Author-email: Seu Nome <seu@email.com>
License: MIT
Requires-Dist: yfinance>=0.2.18
Requires-Dist: pandas>=1.5
Requires-Dist: numpy>=1.24
Requires-Dist: tensorflow>=2.12
Requires-Dist: scikit-learn>=1.2
Requires-Dist: python-dotenv>=1.0
